webdriver_cache_manager_mnawaz6935/__init__.py
webdriver_cache_manager_mnawaz6935/webdriver_cache_manager.py
webdriver_cache_manager_mnawaz6935-0.0.1.dist-info/LICENSE
webdriver_cache_manager_mnawaz6935-0.0.1.dist-info/METADATA
webdriver_cache_manager_mnawaz6935-0.0.1.dist-info/WHEEL
webdriver_cache_manager_mnawaz6935-0.0.1.dist-info/top_level.txt
webdriver_cache_manager_mnawaz6935-0.0.1.dist-info/RECORD
