Metadata-Version: 2.1
Name: webdriver-cache-manager-mnawaz6935
Version: 0.0.1
Summary: Optimize WebDriver usage in Selenium with Python. Manage processes, terminate efficiently, and handle PIDs using CSV. Simplify automation!
Author-email: Muhammad Nawaz <MNawaz6935@gmail.com>
Project-URL: Homepage, https://github.com/mnawaz6935/webdriver_cache_manager
Project-URL: Issues, https://github.com/mnawaz6935/webdriver_cache_manager/issues
Classifier: Programming Language :: Python :: 3
Classifier: License :: OSI Approved :: MIT License
Classifier: Operating System :: OS Independent
Requires-Python: >=3.8
License-File: LICENSE
